QF_sync_agents/SC_qubit_datastruct_v0_clean_data.py
QF_sync_agents/SC_qubit_datastruct_v0_config.py
QF_sync_agents/SC_qubit_datastruct_v0_sync.py
QF_sync_agents/SC_qubit_datastruct_v1_config.py
QF_sync_agents/SC_qubit_datastruct_v1_sync.py
QF_sync_agents/__init__.py
QF_sync_agents/characterization/__init__.py
QF_sync_agents/characterization/csv_conversion_test.py
QF_sync_agents/characterization/sync_characterization.py
QF_sync_agents/characterization/sync_characterization_config.py
QF_sync_agents-0.1.0.dist-info/METADATA
QF_sync_agents-0.1.0.dist-info/WHEEL
QF_sync_agents-0.1.0.dist-info/top_level.txt
QF_sync_agents-0.1.0.dist-info/RECORD
