Metadata-Version: 2.1
Name: QF_sync_agents
Version: 0.1.0
Summary: Collection of sync agents for the software used in QF
Requires-Python: >=3.8
Requires-Dist: etiket-client
